addepar_redflag/__init__.py
addepar_redflag/__main__.py
addepar_redflag/evaluate.py
addepar_redflag/models/__init__.py
addepar_redflag/models/prompts/__init__.py
addepar_redflag/models/prompts/response_models.py
addepar_redflag/models/structures/PullRequest.py
addepar_redflag/models/structures/Result.py
addepar_redflag/models/structures/Ticket.py
addepar_redflag/models/structures/__init__.py
addepar_redflag/redflag.py
addepar_redflag/templates/results.html.jinja2
addepar_redflag/util/__init__.py
addepar_redflag/util/aws.py
addepar_redflag/util/cli.py
addepar_redflag/util/config.py
addepar_redflag/util/console.py
addepar_redflag/util/github.py
addepar_redflag/util/jira.py
addepar_redflag/util/llm.py
addepar_redflag/util/slack.py
addepar_redflag-1.2.0.dist-info/LICENSE.md
addepar_redflag-1.2.0.dist-info/METADATA
addepar_redflag-1.2.0.dist-info/WHEEL
addepar_redflag-1.2.0.dist-info/entry_points.txt
addepar_redflag-1.2.0.dist-info/RECORD
