Metadata-Version: 2.1
Name: addepar-redflag
Version: 1.2.0
Summary: RedFlag uses AI to identify high-risk code changes. Run it in batch mode for release candidate testing or in CI pipelines to flag commits and add reviewers. RedFlag's flexible configuration makes it valuable for any team.
Home-page: https://github.com/Addepar/RedFlag
License: MIT
Keywords: security,code review,static analysis,AI
Author: Addepar Security Engineering
Author-email: security-engineering@addepar.com
Requires-Python: >=3.11,<4.0
Classifier: Environment :: Console
Classifier: Intended Audience :: Developers
Classifier: Intended Audience :: Information Technology
Classifier: License :: OSI Approved :: MIT License
Classifier: Natural Language :: English
Classifier: Operating System :: OS Independent
Classifier: Programming Language :: Python
Classifier: Programming Language :: Python :: 3
Classifier: Programming Language :: Python :: 3.11
Classifier: Programming Language :: Python :: 3.12
Classifier: Programming Language :: Python :: 3.13
Classifier: Topic :: Security
Classifier: Topic :: Software Development
Classifier: Topic :: Software Development :: Quality Assurance
Classifier: Topic :: Software Development :: Testing
Requires-Dist: anthropic (>=0.7.5,<0.8.0)
Requires-Dist: atlassian-python-api (>=3.41.3,<4.0.0)
Requires-Dist: boto3 (>=1.28.79,<2.0.0)
Requires-Dist: click (>=8.1.7,<9.0.0)
Requires-Dist: colorama (>=0.4.6,<0.5.0)
Requires-Dist: gitpython (>=3.1.40,<4.0.0)
Requires-Dist: jinja2 (>=3.1.2,<4.0.0)
Requires-Dist: langchain (>=0.1.13,<0.2.0)
Requires-Dist: langchain-community (>=0.0.29,<0.0.30)
Requires-Dist: langchain-core (>=0.1.34,<0.2.0)
Requires-Dist: pathlib (>=1.0.1,<2.0.0)
Requires-Dist: pygithub (>=2.1.1,<3.0.0)
Requires-Dist: python-dotenv (>=1.0.1,<2.0.0)
Requires-Dist: rich (>=13.7.1,<14.0.0)
Requires-Dist: tenacity (==8.3.0)
Requires-Dist: tiktoken (>=0.5.2,<0.6.0)
Requires-Dist: urllib3 (>=2.2.1,<3.0.0)
Project-URL: Repository, https://github.com/Addepar/RedFlag
